devpi_metawheel/__init__.py
devpi_metawheel/main.py
devpi_metawheel-0.3.dist-info/DESCRIPTION.rst
devpi_metawheel-0.3.dist-info/METADATA
devpi_metawheel-0.3.dist-info/RECORD
devpi_metawheel-0.3.dist-info/WHEEL
devpi_metawheel-0.3.dist-info/entry_points.txt
devpi_metawheel-0.3.dist-info/metadata.json
devpi_metawheel-0.3.dist-info/top_level.txt
