Metadata-Version: 2.0
Name: devpi-metawheel
Version: 0.3
Summary: devpi-server plugin
Requires-Dist: packaging (>=15.3)
